rd_cdm/.DS_Store
rd_cdm/__init__.py
rd_cdm/instances/v2_0_2/code_systems.yaml
rd_cdm/instances/v2_0_2/csvs/code_systems.csv
rd_cdm/instances/v2_0_2/csvs/data_elements.csv
rd_cdm/instances/v2_0_2/csvs/rd_cdm_v2_0_1.csv
rd_cdm/instances/v2_0_2/csvs/value_sets.csv
rd_cdm/instances/v2_0_2/data_elements.yaml
rd_cdm/instances/v2_0_2/jsons/code_systems.json
rd_cdm/instances/v2_0_2/jsons/data_elements.json
rd_cdm/instances/v2_0_2/jsons/rd_cdm_v2_0_1.json
rd_cdm/instances/v2_0_2/jsons/value_sets.json
rd_cdm/instances/v2_0_2/rd_cdm_v2_0_1.yaml
rd_cdm/instances/v2_0_2/value_sets.yaml
rd_cdm/python_classes/rd_cdm.py
rd_cdm/python_classes/rd_cdm_pydantic.py
rd_cdm/schema/rd_cdm.yaml
rd_cdm/utils/config.py
rd_cdm/utils/csv_parsing.py
rd_cdm/utils/gen_pydantic.py
rd_cdm/utils/json_parsing.py
rd_cdm/utils/merge_instances.py
rd_cdm/utils/settings.py
rd_cdm/utils/validation.py
rd_cdm/utils/validation_utils.py
rd_cdm/utils/versioning.py
rd_cdm-2.0.2.dist-info/LICENSE
rd_cdm-2.0.2.dist-info/METADATA
rd_cdm-2.0.2.dist-info/WHEEL
rd_cdm-2.0.2.dist-info/entry_points.txt
rd_cdm-2.0.2.dist-info/RECORD
