Metadata-Version: 2.3
Name: rd-cdm
Version: 2.0.2
Summary: An ontology-based rare disease common data model (RD-CDM) harmonising international registries, HL7 FHIR, and GA4GH Phenopackets.
License: MIT
Keywords: Rare Diseases,Interoperability,Ontology,GA4GH Phenopackets,HL7 FHIR,International Patient Summary,Genomics Reporting
Author: Adam SL Graefe
Author-email: adam.graefe@charite.de
Requires-Python: >=3.10,<3.13
Classifier: Development Status :: 3 - Alpha
Classifier: Intended Audience :: Science/Research
Classifier: License :: OSI Approved :: MIT License
Classifier: Operating System :: OS Independent
Classifier: Programming Language :: Python :: 3
Classifier: Programming Language :: Python :: 3.10
Classifier: Programming Language :: Python :: 3.11
Classifier: Programming Language :: Python :: 3.12
Classifier: Topic :: Scientific/Engineering :: Medical Science Apps.
Provides-Extra: docs
Provides-Extra: test
Requires-Dist: jsonschema
Requires-Dist: linkml (>=1.7.0)
Requires-Dist: linkml-runtime (>=1.9.4)
Requires-Dist: numpy
Requires-Dist: oaklib (>=0.6.23)
Requires-Dist: pydantic (>=2.4,<3.0)
Requires-Dist: pydantic-settings (>=2.3,<3.0)
Requires-Dist: pytest (>=7.0.0,<9.0.0) ; extra == "test"
Requires-Dist: requests (>=2.31.0,<3.0.0)
Requires-Dist: requests-cache (>=1.2.1,<2.0.0)
Requires-Dist: requests-mock (>=1.11.0) ; extra == "test"
Requires-Dist: ruamel.yaml (>=0.17.21)
Requires-Dist: sphinx (>=7.0.0) ; extra == "docs"
Requires-Dist: sphinx-copybutton (>=0.5.0) ; extra == "docs"
Requires-Dist: sphinx-rtd-theme (>=1.3.0) ; extra == "docs"
Project-URL: Documentation, https://rd-cdm.readthedocs.io/en/latest/
Project-URL: Homepage, https://github.com/BIH-CEI/rd-cdm
Project-URL: Repository, https://github.com/BIH-CEI/rd-cdm
